pet/__init__.py
pet/asdfas.py
pet/bts.py
pet/classifier.py
pet/exceptions.py
pet/models.py
pet/perlre.py
pet/pet_update.py
pet/serve.py
pet/sql.py
pet/update.py
pet/vcs.py
pet/watch.py
pet/web/__init__.py
pet/web/views.py
pet/web/static/default.css
pet/web/static/overview.js
pet/web/templates/changelog.pt
pet/web/templates/overview.pt
pet_debian-1.2.74.dist-info/DESCRIPTION.rst
pet_debian-1.2.74.dist-info/METADATA
pet_debian-1.2.74.dist-info/RECORD
pet_debian-1.2.74.dist-info/WHEEL
pet_debian-1.2.74.dist-info/entry_points.txt
pet_debian-1.2.74.dist-info/metadata.json
pet_debian-1.2.74.dist-info/top_level.txt
